README.txt
setup.py
docs/HISTORY.txt
zopyx/__init__.py
zopyx.trashfinder.egg-info/PKG-INFO
zopyx.trashfinder.egg-info/SOURCES.txt
zopyx.trashfinder.egg-info/dependency_links.txt
zopyx.trashfinder.egg-info/entry_points.txt
zopyx.trashfinder.egg-info/namespace_packages.txt
zopyx.trashfinder.egg-info/not-zip-safe
zopyx.trashfinder.egg-info/requires.txt
zopyx.trashfinder.egg-info/top_level.txt
zopyx/trashfinder/__init__.py
zopyx/trashfinder/cli.py