Metadata-Version: 1.0
Name: zopyx.trashfinder
Version: 0.1.4
Summary: Find package trash on PyPI
Home-page: http://pypi.python.org/pypi/zopyx.trashfinder
Author: Andreas Jung
Author-email: info@zopyx.com
License: ZPL
Keywords: Trash Crap PyPI
Platform: UNKNOWN
Classifier: Programming Language :: Python
